wps/__init__.py
wps-0.1.0.dist-info/WHEEL
wps-0.1.0.dist-info/METADATA
wps-0.1.0.dist-info/RECORD
